__init__.py
django_percentagefield/__init__.py
django_percentagefield/apps.py
django_percentagefield/utils.py
django_percentagefield/db/__init__.py
django_percentagefield/db/models/__init__.py
django_percentagefield/db/models/fields/__init__.py
django_percentagefield/db/models/fields/percentage_field.py
django_percentagefield/forms/__init__.py
django_percentagefield/forms/widgets.py
django_percentagefield/templates/django_percentagefield/forms/widgets/percentage.html
django_percentagefield-0.1.7.dist-info/LICENSE
django_percentagefield-0.1.7.dist-info/METADATA
django_percentagefield-0.1.7.dist-info/WHEEL
django_percentagefield-0.1.7.dist-info/top_level.txt
django_percentagefield-0.1.7.dist-info/RECORD
