Metadata-Version: 2.1
Name: django-percentagefield
Version: 0.1.7
Summary: A ``PercentageField`` for Django that shows a Decimal (ex. ``0.2100`` in the database - by default rounded to 4 decimal spaces) as a percentage in the admin (ex. ``21%``). With built-in (overridable) min and max validator to ensure a valid percentage range: 0 ≤ x ≤ 100.
Author-email: Nico Vromans <nico.vromans@alpinedigital.be>, Alpine Digital <contact@alpinedigital.be>
Project-URL: Homepage, https://github.com/alpine-digital/django-percentagefield
Project-URL: Issues, https://github.com/alpine-digital/django-percentagefield/issues
Classifier: Environment :: Web Environment
Classifier: Framework :: Django :: 5.0
Classifier: Operating System :: OS Independent
Classifier: Intended Audience :: Developers
Classifier: License :: OSI Approved :: MIT License
Classifier: Programming Language :: Python :: 3 :: Only
Classifier: Programming Language :: Python :: 3.12
Classifier: Topic :: Internet :: WWW/HTTP
Classifier: Topic :: Software Development :: Libraries :: Application Frameworks
Classifier: Topic :: Software Development :: Libraries :: Python Modules
Requires-Python: >=3.12
License-File: LICENSE
Requires-Dist: django>=5.0.6
